[{"id":7,"name":"Dilnaz","surname":"Khuzhan","email":"qwer@gmail.com","roles":[{"id":7,"name":"USER"}]},{"id":10,"name":"Fariza","surname":"Bukharova","email":"asdfghjjf@gmail.com","roles":[{"id":10,"name":"ADMIN"}]},{"id":11,"name":"Gulnaz","surname":"Kaldarbek","email":"zxcvbnm@gmail.com","roles":[{"id":10,"name":"ADMIN"},{"id":11,"name":"SUPER_ADMIN"}]},{"id":13,"name":"Gulbarshyn","surname":"valikhan","email":"sdfg@gmail.com","roles":[]},{"id":12,"name":"zsdxfcvgbn","surname":"werty","email":"qwerr@narxoz.com","roles":[]},{"id":14,"name":"xcvbn","surname":"dgddggd","email":"sdsf@narxoz.kz","roles":[]},{"id":15,"name":"gul","surname":"gul","email":"ghjk@narxoz.kz","roles":[]},{"id":16,"name":"Gulbarshyn","surname":"Valikhan","email":"dfgh@narxoz.kz","roles":[]}]